caradoc/__about__.py
caradoc/__init__.py
caradoc/utils/__init__.py
caradoc/utils/dataoutput.py
caradoc/utils/financialyear.py
caradoc-0.3.0.dist-info/METADATA
caradoc-0.3.0.dist-info/WHEEL
caradoc-0.3.0.dist-info/licenses/LICENSE
caradoc-0.3.0.dist-info/RECORD
