Metadata-Version: 2.4
Name: caradoc
Version: 0.3.0
Summary: A suite of tools to help with data analysis in python.
Project-URL: Documentation, https://github.com/kanedata/caradoc#readme
Project-URL: Issues, https://github.com/kanedata/caradoc/issues
Project-URL: Source, https://github.com/kanedata/caradoc
Author-email: David Kane <david@dkane.net>
License-Expression: MIT
License-File: LICENSE
Classifier: Development Status :: 3 - Alpha
Classifier: Programming Language :: Python
Classifier: Programming Language :: Python :: 3.9
Classifier: Programming Language :: Python :: 3.10
Classifier: Programming Language :: Python :: 3.11
Classifier: Programming Language :: Python :: 3.12
Classifier: Programming Language :: Python :: 3.13
Classifier: Programming Language :: Python :: Implementation :: CPython
Classifier: Programming Language :: Python :: Implementation :: PyPy
Requires-Python: >=3.9
Requires-Dist: openpyxl
Requires-Dist: pandas
Requires-Dist: xlsxwriter
